[{"name":"Tachiyomi: MangaFire","pkg":"eu.kanade.tachiyomi.extension.all.mangafire","apk":"tachiyomi-all.mangafire-v1.4.16.apk","lang":"all","code":16,"version":"1.4.16","nsfw":1,"hasReadme":0,"hasChangelog":0,"icon":"icon/eu.kanade.tachiyomi.extension.all.mangafire.png","sig":"212199045691887b32eb2397f167f4b7d53a73131119975df9914595bc95880a","sources":[{"name":"MangaFire","id":"1695572115","lang":"all","baseUrl":"https://mangafire.to"}],"sha256":"12d8279d14c3a894a98c0b1cfcc9af585a9c91be4465df5baa430e19fb070f86"},{"name":"Tachiyomi: Comix","pkg":"eu.kanade.tachiyomi.extension.en.comix","apk":"tachiyomi-en.comix-v1.4.110.apk","lang":"en","code":110,"version":"1.4.110","nsfw":1,"hasReadme":0,"hasChangelog":0,"icon":"icon/eu.kanade.tachiyomi.extension.en.comix.png","sig":"212199045691887b32eb2397f167f4b7d53a73131119975df9914595bc95880a","sources":[{"name":"Comix","id":"7537715367149829912","lang":"en","baseUrl":"https://comix.to"}],"sha256":"ccacd698dfd6252e84d2c8ec8c48a8c63b8daf4b0eae9cac2c7810e85dcefc89"},{"name":"Tachiyomi: Like Manga","pkg":"eu.kanade.tachiyomi.extension.en.likemanga","apk":"tachiyomi-en.likemanga-v1.4.106.apk","lang":"en","code":106,"version":"1.4.106","nsfw":1,"hasReadme":0,"hasChangelog":0,"icon":"icon/eu.kanade.tachiyomi.extension.en.likemanga.png","sig":"212199045691887b32eb2397f167f4b7d53a73131119975df9914595bc95880a","sources":[{"name":"Like Manga","id":"411833355147795520","lang":"en","baseUrl":"https://likemanga.ink"}],"sha256":"c6e5b05cec186cdf2e80b23943c5238442e1d6edcd012cf22f75aa1dc8112248"}]